PythonOpencvJisuanjiShijueXiangmuChuyiFix1/README.md
PythonOpencvJisuanjiShijueXiangmuChuyiFix1/__init__.py
PythonOpencvJisuanjiShijueXiangmuChuyiFix1/__main__.py
PythonOpencvJisuanjiShijueXiangmuChuyiFix1/file.epub
PythonOpencvJisuanjiShijueXiangmuChuyiFix1/index.html
PythonOpencvJisuanjiShijueXiangmuChuyiFix1/css/__init__.py
PythonOpencvJisuanjiShijueXiangmuChuyiFix1/css/annotations.css
PythonOpencvJisuanjiShijueXiangmuChuyiFix1/css/main.css
PythonOpencvJisuanjiShijueXiangmuChuyiFix1/css/normalize.css
PythonOpencvJisuanjiShijueXiangmuChuyiFix1/css/popup.css
PythonOpencvJisuanjiShijueXiangmuChuyiFix1/font/__init__.py
PythonOpencvJisuanjiShijueXiangmuChuyiFix1/font/fontello.eot
PythonOpencvJisuanjiShijueXiangmuChuyiFix1/font/fontello.svg
PythonOpencvJisuanjiShijueXiangmuChuyiFix1/font/fontello.ttf
PythonOpencvJisuanjiShijueXiangmuChuyiFix1/font/fontello.woff
PythonOpencvJisuanjiShijueXiangmuChuyiFix1/img/__init__.py
PythonOpencvJisuanjiShijueXiangmuChuyiFix1/img/annotator-glyph-sprite.png
PythonOpencvJisuanjiShijueXiangmuChuyiFix1/img/annotator-icon-sprite.png
PythonOpencvJisuanjiShijueXiangmuChuyiFix1/img/apple-touch-icon.png
PythonOpencvJisuanjiShijueXiangmuChuyiFix1/img/cancelfullscreen.png
PythonOpencvJisuanjiShijueXiangmuChuyiFix1/img/close.png
PythonOpencvJisuanjiShijueXiangmuChuyiFix1/img/fullscreen.png
PythonOpencvJisuanjiShijueXiangmuChuyiFix1/img/loader.gif
PythonOpencvJisuanjiShijueXiangmuChuyiFix1/img/menu-icon.png
PythonOpencvJisuanjiShijueXiangmuChuyiFix1/img/save.png
PythonOpencvJisuanjiShijueXiangmuChuyiFix1/img/saved.png
PythonOpencvJisuanjiShijueXiangmuChuyiFix1/img/settings-s.png
PythonOpencvJisuanjiShijueXiangmuChuyiFix1/img/settings.png
PythonOpencvJisuanjiShijueXiangmuChuyiFix1/img/star.png
PythonOpencvJisuanjiShijueXiangmuChuyiFix1/js/__init__.py
PythonOpencvJisuanjiShijueXiangmuChuyiFix1/js/epub.js
PythonOpencvJisuanjiShijueXiangmuChuyiFix1/js/epub.min.js
PythonOpencvJisuanjiShijueXiangmuChuyiFix1/js/epub.min.map
python_opencv_jisuanji_shijue_xiangmu_chuyi_fix1-2025.3.25.0.dist-info/METADATA
python_opencv_jisuanji_shijue_xiangmu_chuyi_fix1-2025.3.25.0.dist-info/WHEEL
python_opencv_jisuanji_shijue_xiangmu_chuyi_fix1-2025.3.25.0.dist-info/entry_points.txt
python_opencv_jisuanji_shijue_xiangmu_chuyi_fix1-2025.3.25.0.dist-info/top_level.txt
python_opencv_jisuanji_shijue_xiangmu_chuyi_fix1-2025.3.25.0.dist-info/RECORD
